{"code":200,
"data":{
  "title":"程序喵的复仇之路",
  "id":"20161029",
  "author":"宅女",
  "time":"2016-10-29",
  "desc":"产品汪，像平时一样准备产品稿产品汪，像平时一样准备产品稿~",
  "type":"5",
  "body":"",
  "article":{
    "articleClassName":"items_5",
    "start":[
      {
        "desc":"",
        "imagesUrl":""
      }
    ],
    "articleBody":[
      {
        "title":"产品汪，像平时一样准备产品稿~",
        "desc":"<p class='ta_c'>▼</p>",
        "code":"",
        "imagesUrl":"3.jpg",
        "imagesDesc":""
      },
      {
        "title":"这时，程序喵过来了~",
        "desc":"<p class='ta_c'>▼</p>",
        "code":"",
        "imagesUrl":"4.jpg",
        "imagesDesc":"",
        "ends":""
      },
      {
        "title":"程序喵：柴柴，腻粗来下~",
        "desc":"<p class='ta_c'>▼</p>",
        "code":"",
        "imagesUrl":"5.jpg",
        "imagesDesc":"",
        "ends":""
      },
      {
        "title":"产品汪：怎么啦？",
        "desc":"<p class='ta_c'>▼</p>",
        "code":"",
        "imagesUrl":"6.jpg",
        "imagesDesc":"",
        "ends":""
      },
      {
        "title":"程序喵：没事，老板叫腻~",
        "desc":"<p class='ta_c'>▼</p>",
        "code":"",
        "imagesUrl":"7.jpg",
        "imagesDesc":"",
        "ends":""
      },
      {
        "title":"程序喵：机会来了！",
        "desc":"<p class='ta_c'>▼</p>",
        "code":"",
        "imagesUrl":"8.jpg",
        "imagesDesc":"",
        "ends":""
      },
      {
        "title":"程序喵：他喵的，催催催，改改改，指指指，真最讨厌别人戳朕屏幕了，You Can You Up ！",
        "desc":"<p class='ta_c'>▼</p>",
        "code":"",
        "imagesUrl":"9.jpg",
        "imagesDesc":"",
        "ends":""
      },
      {
        "title":"程序喵：看腻下次还戳朕屏幕不！",
        "desc":"<p class='ta_c'>▼</p>",
        "code":"",
        "imagesUrl":"10.jpg",
        "imagesDesc":"",
        "ends":""
      },
      {
        "title":"产品汪：发生了什么？？？[懵逼脸]",
        "desc":"<p class='ta_c'>▼</p>",
        "code":"",
        "imagesUrl":"11.jpg",
        "imagesDesc":""
      }
    ],
    "end":[
    ]
  }
},
"error":"Success",
"status":"SUCESS"
}